README.md
setup.py
samplesxsdas/Indices.py
samplesxsdas/Raos.py
samplesxsdas/Visual.py
samplesxsdas/__init__.py
samplesxsdas.egg-info/PKG-INFO
samplesxsdas.egg-info/SOURCES.txt
samplesxsdas.egg-info/dependency_links.txt
samplesxsdas.egg-info/requires.txt
samplesxsdas.egg-info/top_level.txt